CHANGES.md
CONTRIBUTORS.txt
LICENSE
README.md
bootstrap.py
buildout.cfg
setup.py
src/uncsom/__init__.py
src/uncsom.recipe.ploneupdater.egg-info/PKG-INFO
src/uncsom.recipe.ploneupdater.egg-info/SOURCES.txt
src/uncsom.recipe.ploneupdater.egg-info/dependency_links.txt
src/uncsom.recipe.ploneupdater.egg-info/entry_points.txt
src/uncsom.recipe.ploneupdater.egg-info/namespace_packages.txt
src/uncsom.recipe.ploneupdater.egg-info/not-zip-safe
src/uncsom.recipe.ploneupdater.egg-info/requires.txt
src/uncsom.recipe.ploneupdater.egg-info/top_level.txt
src/uncsom/recipe/__init__.py
src/uncsom/recipe/ploneupdater/README.txt
src/uncsom/recipe/ploneupdater/__init__.py
src/uncsom/recipe/ploneupdater/ploneupdater.py
src/uncsom/recipe/ploneupdater/tests/__init__.py
src/uncsom/recipe/ploneupdater/tests/test_docs.py