Metadata-Version: 1.1
Name: uncsom.recipe.ploneupdater
Version: 1.5
Summary: A buildout recipe to update plone sites
Home-page: https://github.com/ianderso/uncsom.recipe.ploneupdater
Author: Ian Anderson
Author-email: ianderso@med.unc.edu
License: GPL
Keywords: buildout recipe update plone
Platform: UNKNOWN
Classifier: Framework :: Buildout
Classifier: Intended Audience :: Developers
Classifier: Intended Audience :: System Administrators
Classifier: Programming Language :: Python
Classifier: Programming Language :: Python :: 2.6
Classifier: Programming Language :: Python :: 2.7
Classifier: Topic :: Software Development :: Build Tools
Classifier: Topic :: Software Development :: Libraries :: Python Modules
Classifier: License :: OSI Approved :: GNU General Public License (GPL)
